Workbook

Sheet Sheet1
A1: Key Assumptions
A2: Item | B2: Value | C2: Notes
A3: Current Share Price | B3: 255.52 | C3: Latest market price
A4: Shares Outstanding (m) | B4: 14773260000 | C4: From data
A5: Base Year Dividend | B5: 0.26 | C5: Dividend per share
A6: Dividend Growth Rate | B6: 0.05 | C6: Annual dividend growth assumption
A7: Discount Rate | B7: 0.07 | C7: Required return
A8: Terminal Growth Rate | B8: 0.03 | C8: Long-term growth

Sheet Sheet2
A1: Dividend Projection (Years 1-5)
A2: Year | B2: Dividend per share | C2: Present Value Factor | D2: Present Value of Dividend
A3: 1 | B3: =0.26 * 1.05 -> 0.273 | C3: =1/(1+0.07)^1 -> 0.93457944 | D3: =B3*C3 -> 0.25514019
A4: 2 | B4: =B3 * 1.05 -> 0.28665 | C4: =1/(1+0.07)^2 -> 0.87343873 | D4: =B4*C4 -> 0.25037121
A5: 3 | B5: =B4 * 1.05 -> 0.3009825 | C5: =1/(1+0.07)^3 -> 0.81629788 | D5: =B5*C5 -> 0.24569138
A6: 4 | B6: =B5 * 1.05 -> 0.31603163 | C6: =1/(1+0.07)^4 -> 0.76289521 | D6: =B6*C6 -> 0.24109901
A7: 5 | B7: =B6 * 1.05 -> 0.33183321 | C7: =1/(1+0.07)^5 -> 0.71298618 | D7: =B7*C7 -> 0.23659249
A9: Sum PV of dividends | D9: =SUM(D3:D7) -> 1.2288943

Sheet Sheet3
A1: Terminal Value at Year 5
A2: Year | B2: Terminal Value per share | C2: PV of Terminal Value per share
A3: 5 | B3: =(Sheet2!B7 * (1 + 0.03))/(0.07-0.03) -> 8.5447051 | C3: =8.54/(1 + 0.07)^5 -> 6.088902

Sheet Sheet4
A1: Equity Value & Implied Share Price
A2: Item | B2: Value
A3: Total PV of Dividends | B3: =Sheet2!D9 -> 1.2288943
A4: PV of Terminal Value | B4: =Sheet3!C3 -> 6.088902
A5: Total Equity Value per Share | B5: =B3 + B4 -> 7.3177963

Sheet Sheet5
A1: Sensitivity Table (PV per Share)
A2: Growth Rate/ Discount Rate | B2: 0.06 | C2: 0.07 | D2: 8
A3: 0.04 | B3: =(Sheet2!D9) + (0.332 * (1+0.04)/(0.06-0.04)/(1+0.06)^5) -> 14.129559 | C3: 12.5 | D3: 11
A4: 0.05 | B4: =(Sheet2!D9) + (0.332 * (1+0.05)/(0.06-0.05)/(1+0.06)^5) -> 27.278314 | C4: 21 | D4: 18.33
A5: 0.06 | B5: =(Sheet2!D9) + (0.332 * (1+0.06)/(0.07-0.06)/(1+0.06)^5) -> 27.526404 | C5: 22 | D5: 19.5
