Workbook

Sheet Assumptions
A1: Apple Inc. (AAPL) – Dividend Discount Model Assumptions
A2: Item | B2: Value | C2: Notes / source
A3: Current Share Price ($) | B3: 255.52 | C3: Author’s figure at time of analysis
A4: Shares Outstanding (m) | B4: 14773 | C4: ≈14.77bn shares (author’s data)
A5: Quarterly Dividend per Share ($) | B5: 0.26 | C5: Apple pays dividends quarterly: confirm latest declared amount
A6: Annual Dividend (D0, $) | B6: =B5*4 -> 1.04 | C6: Quarterly × 4
A7: Dividend Growth Rate (Years 1–5) | B7: 0.05 | C7: Assumption
A8: Discount Rate (Required Return) | B8: 0.07 | C8: Assumption
A9: Terminal Growth Rate | B9: 0.03 | C9: Long-term growth assumption

Sheet Dividend Projection
A1: Dividend Projection (Years 1–5)
A2: Year | B2: Dividend per Share ($) | C2: PV Factor | D2: PV of Dividend ($)
A3: 1 | B3: =Assumptions!B6*(1+Assumptions!$B$7) -> 1.092 | C3: =1/(1+Assumptions!$B$8)^1 -> 0.93457944 | D3: =B3*C3 -> 1.0205607
A4: 2 | B4: =B3*(1+Assumptions!$B$7) -> 1.1466 | C4: =1/(1+Assumptions!$B$8)^2 -> 0.87343873 | D4: =B4*C4 -> 1.0014848
A5: 3 | B5: =B4*(1+Assumptions!$B$7) -> 1.20393 | C5: =1/(1+Assumptions!$B$8)^3 -> 0.81629788 | D5: =B5*C5 -> 0.9827655
A6: 4 | B6: =B5*(1+Assumptions!$B$7) -> 1.2641265 | C6: =1/(1+Assumptions!$B$8)^4 -> 0.76289521 | D6: =B6*C6 -> 0.96439605
A7: 5 | B7: =B6*(1+Assumptions!$B$7) -> 1.3273328 | C7: =1/(1+Assumptions!$B$8)^5 -> 0.71298618 | D7: =B7*C7 -> 0.94636996
A9: Sum of PV of dividends | D9: =SUM(D3:D7) -> 4.9155771

Sheet Valuation
A1: Terminal Value, Equity Value & Comparison to Market
A2: Item | B2: Value ($)
A3: Terminal Value at Year 5 | B3: ='Dividend Projection'!B7*(1+Assumptions!B9)/(Assumptions!B8-Assumptions!B9) -> 34.17882
A4: PV of Terminal Value | B4: =B3/(1+Assumptions!B8)^5 -> 24.369026
A5: PV of Dividends (Years 1–5) | B5: ='Dividend Projection'!D9 -> 4.9155771
A6: Intrinsic Value per Share (DDM) | B6: =B4+B5 -> 29.284604
A7: Current Share Price | B7: =Assumptions!B3 -> 255.52
A8: DDM value as % of market price | B8: =B6/B7 -> 0.11460787

Sheet Sensitivity
A1: Intrinsic Value per Share ($): Discount Rate vs Terminal Growth
A2: Rows: terminal growth. Columns: discount rate. Each cell recalculates the full model.
A3: g \ r | B3: 0.06 | C3: 0.07 | D3: 0.08 | E3: 0.09
A4: 0.02 | B4: =IF(B$3<=$A4,"n/a",(Assumptions!$B$6*(1+Assumptions!$B$7)^1/(1+B$3)^1+Assumptions!$B$6*(1+Assumptions!$B$7)^2/(1+B$3)^2+Assumptions!$B$6*(1+Assumptions!$B$7)^3/(1+B$3)^3+Assumptions!$B$6*(1+Assumptions!$B$7)^4/(1+B$3)^4+Assumptions!$B$6*(1+Assumptions!$B$7)^5/(1+B$3)^5)+Assumptions!$B$6*(1+Assumptions!$B$7)^5*(1+$A4)/(B$3-$A4)/(1+B$3)^5) -> 30.347106 | C4: =IF(C$3<=$A4,"n/a",(Assumptions!$B$6*(1+Assumptions!$B$7)^1/(1+C$3)^1+Assumptions!$B$6*(1+Assumptions!$B$7)^2/(1+C$3)^2+Assumptions!$B$6*(1+Assumptions!$B$7)^3/(1+C$3)^3+Assumptions!$B$6*(1+Assumptions!$B$7)^4/(1+C$3)^4+Assumptions!$B$6*(1+Assumptions!$B$7)^5/(1+C$3)^5)+Assumptions!$B$6*(1+Assumptions!$B$7)^5*(1+$A4)/(C$3-$A4)/(1+C$3)^5) -> 24.221524 | D4: =IF(D$3<=$A4,"n/a",(Assumptions!$B$6*(1+Assumptions!$B$7)^1/(1+D$3)^1+Assumptions!$B$6*(1+Assumptions!$B$7)^2/(1+D$3)^2+Assumptions!$B$6*(1+Assumptions!$B$7)^3/(1+D$3)^3+Assumptions!$B$6*(1+Assumptions!$B$7)^4/(1+D$3)^4+Assumptions!$B$6*(1+Assumptions!$B$7)^5/(1+D$3)^5)+Assumptions!$B$6*(1+Assumptions!$B$7)^5*(1+$A4)/(D$3-$A4)/(1+D$3)^5) -> 20.139512 | E4: =IF(E$3<=$A4,"n/a",(Assumptions!$B$6*(1+Assumptions!$B$7)^1/(1+E$3)^1+Assumptions!$B$6*(1+Assumptions!$B$7)^2/(1+E$3)^2+Assumptions!$B$6*(1+Assumptions!$B$7)^3/(1+E$3)^3+Assumptions!$B$6*(1+Assumptions!$B$7)^4/(1+E$3)^4+Assumptions!$B$6*(1+Assumptions!$B$7)^5/(1+E$3)^5)+Assumptions!$B$6*(1+Assumptions!$B$7)^5*(1+$A4)/(E$3-$A4)/(1+E$3)^5) -> 17.225185
A5: 0.025 | B5: =IF(B$3<=$A5,"n/a",(Assumptions!$B$6*(1+Assumptions!$B$7)^1/(1+B$3)^1+Assumptions!$B$6*(1+Assumptions!$B$7)^2/(1+B$3)^2+Assumptions!$B$6*(1+Assumptions!$B$7)^3/(1+B$3)^3+Assumptions!$B$6*(1+Assumptions!$B$7)^4/(1+B$3)^4+Assumptions!$B$6*(1+Assumptions!$B$7)^5/(1+B$3)^5)+Assumptions!$B$6*(1+Assumptions!$B$7)^5*(1+$A5)/(B$3-$A5)/(1+B$3)^5) -> 34.102006 | C5: =IF(C$3<=$A5,"n/a",(Assumptions!$B$6*(1+Assumptions!$B$7)^1/(1+C$3)^1+Assumptions!$B$6*(1+Assumptions!$B$7)^2/(1+C$3)^2+Assumptions!$B$6*(1+Assumptions!$B$7)^3/(1+C$3)^3+Assumptions!$B$6*(1+Assumptions!$B$7)^4/(1+C$3)^4+Assumptions!$B$6*(1+Assumptions!$B$7)^5/(1+C$3)^5)+Assumptions!$B$6*(1+Assumptions!$B$7)^5*(1+$A5)/(C$3-$A5)/(1+C$3)^5) -> 26.471782 | D5: =IF(D$3<=$A5,"n/a",(Assumptions!$B$6*(1+Assumptions!$B$7)^1/(1+D$3)^1+Assumptions!$B$6*(1+Assumptions!$B$7)^2/(1+D$3)^2+Assumptions!$B$6*(1+Assumptions!$B$7)^3/(1+D$3)^3+Assumptions!$B$6*(1+Assumptions!$B$7)^4/(1+D$3)^4+Assumptions!$B$6*(1+Assumptions!$B$7)^5/(1+D$3)^5)+Assumptions!$B$6*(1+Assumptions!$B$7)^5*(1+$A5)/(D$3-$A5)/(1+D$3)^5) -> 21.617739 | E5: =IF(E$3<=$A5,"n/a",(Assumptions!$B$6*(1+Assumptions!$B$7)^1/(1+E$3)^1+Assumptions!$B$6*(1+Assumptions!$B$7)^2/(1+E$3)^2+Assumptions!$B$6*(1+Assumptions!$B$7)^3/(1+E$3)^3+Assumptions!$B$6*(1+Assumptions!$B$7)^4/(1+E$3)^4+Assumptions!$B$6*(1+Assumptions!$B$7)^5/(1+E$3)^5)+Assumptions!$B$6*(1+Assumptions!$B$7)^5*(1+$A5)/(E$3-$A5)/(1+E$3)^5) -> 18.2585
A6: 0.03 | B6: =IF(B$3<=$A6,"n/a",(Assumptions!$B$6*(1+Assumptions!$B$7)^1/(1+B$3)^1+Assumptions!$B$6*(1+Assumptions!$B$7)^2/(1+B$3)^2+Assumptions!$B$6*(1+Assumptions!$B$7)^3/(1+B$3)^3+Assumptions!$B$6*(1+Assumptions!$B$7)^4/(1+B$3)^4+Assumptions!$B$6*(1+Assumptions!$B$7)^5/(1+B$3)^5)+Assumptions!$B$6*(1+Assumptions!$B$7)^5*(1+$A6)/(B$3-$A6)/(1+B$3)^5) -> 39.108539 | C6: =IF(C$3<=$A6,"n/a",(Assumptions!$B$6*(1+Assumptions!$B$7)^1/(1+C$3)^1+Assumptions!$B$6*(1+Assumptions!$B$7)^2/(1+C$3)^2+Assumptions!$B$6*(1+Assumptions!$B$7)^3/(1+C$3)^3+Assumptions!$B$6*(1+Assumptions!$B$7)^4/(1+C$3)^4+Assumptions!$B$6*(1+Assumptions!$B$7)^5/(1+C$3)^5)+Assumptions!$B$6*(1+Assumptions!$B$7)^5*(1+$A6)/(C$3-$A6)/(1+C$3)^5) -> 29.284604 | D6: =IF(D$3<=$A6,"n/a",(Assumptions!$B$6*(1+Assumptions!$B$7)^1/(1+D$3)^1+Assumptions!$B$6*(1+Assumptions!$B$7)^2/(1+D$3)^2+Assumptions!$B$6*(1+Assumptions!$B$7)^3/(1+D$3)^3+Assumptions!$B$6*(1+Assumptions!$B$7)^4/(1+D$3)^4+Assumptions!$B$6*(1+Assumptions!$B$7)^5/(1+D$3)^5)+Assumptions!$B$6*(1+Assumptions!$B$7)^5*(1+$A6)/(D$3-$A6)/(1+D$3)^5) -> 23.39161 | E6: =IF(E$3<=$A6,"n/a",(Assumptions!$B$6*(1+Assumptions!$B$7)^1/(1+E$3)^1+Assumptions!$B$6*(1+Assumptions!$B$7)^2/(1+E$3)^2+Assumptions!$B$6*(1+Assumptions!$B$7)^3/(1+E$3)^3+Assumptions!$B$6*(1+Assumptions!$B$7)^4/(1+E$3)^4+Assumptions!$B$6*(1+Assumptions!$B$7)^5/(1+E$3)^5)+Assumptions!$B$6*(1+Assumptions!$B$7)^5*(1+$A6)/(E$3-$A6)/(1+E$3)^5) -> 19.464033
A7: 0.035 | B7: =IF(B$3<=$A7,"n/a",(Assumptions!$B$6*(1+Assumptions!$B$7)^1/(1+B$3)^1+Assumptions!$B$6*(1+Assumptions!$B$7)^2/(1+B$3)^2+Assumptions!$B$6*(1+Assumptions!$B$7)^3/(1+B$3)^3+Assumptions!$B$6*(1+Assumptions!$B$7)^4/(1+B$3)^4+Assumptions!$B$6*(1+Assumptions!$B$7)^5/(1+B$3)^5)+Assumptions!$B$6*(1+Assumptions!$B$7)^5*(1+$A7)/(B$3-$A7)/(1+B$3)^5) -> 46.117685 | C7: =IF(C$3<=$A7,"n/a",(Assumptions!$B$6*(1+Assumptions!$B$7)^1/(1+C$3)^1+Assumptions!$B$6*(1+Assumptions!$B$7)^2/(1+C$3)^2+Assumptions!$B$6*(1+Assumptions!$B$7)^3/(1+C$3)^3+Assumptions!$B$6*(1+Assumptions!$B$7)^4/(1+C$3)^4+Assumptions!$B$6*(1+Assumptions!$B$7)^5/(1+C$3)^5)+Assumptions!$B$6*(1+Assumptions!$B$7)^5*(1+$A7)/(C$3-$A7)/(1+C$3)^5) -> 32.901089 | D7: =IF(D$3<=$A7,"n/a",(Assumptions!$B$6*(1+Assumptions!$B$7)^1/(1+D$3)^1+Assumptions!$B$6*(1+Assumptions!$B$7)^2/(1+D$3)^2+Assumptions!$B$6*(1+Assumptions!$B$7)^3/(1+D$3)^3+Assumptions!$B$6*(1+Assumptions!$B$7)^4/(1+D$3)^4+Assumptions!$B$6*(1+Assumptions!$B$7)^5/(1+D$3)^5)+Assumptions!$B$6*(1+Assumptions!$B$7)^5*(1+$A7)/(D$3-$A7)/(1+D$3)^5) -> 25.559675 | E7: =IF(E$3<=$A7,"n/a",(Assumptions!$B$6*(1+Assumptions!$B$7)^1/(1+E$3)^1+Assumptions!$B$6*(1+Assumptions!$B$7)^2/(1+E$3)^2+Assumptions!$B$6*(1+Assumptions!$B$7)^3/(1+E$3)^3+Assumptions!$B$6*(1+Assumptions!$B$7)^4/(1+E$3)^4+Assumptions!$B$6*(1+Assumptions!$B$7)^5/(1+E$3)^5)+Assumptions!$B$6*(1+Assumptions!$B$7)^5*(1+$A7)/(E$3-$A7)/(1+E$3)^5) -> 20.888754

Sheet Interpretation
A1: Why the DDM undervalues Apple
A3: The dividend discount model values a share only on the dividends it pays.
A4: Apple returns most of its cash to shareholders through share buybacks rather than dividends, so its dividend is small relative to its share price.
A5: As a result the DDM produces an intrinsic value far below the market price (see 'DDM value as % of market price' on the Valuation sheet).
A6: This does not mean Apple is overvalued by that amount: it shows the DDM is the wrong tool for a company with a low payout ratio.
A7: A free cash flow DCF (as used for BP) or a total shareholder yield model (dividends + buybacks) would be more appropriate for Apple.
