Workbook

Sheet Assumptions
A1: BP plc (BP.L) – Key Valuation Assumptions
A2: Item | B2: Value | C2: Notes / source
A3: Base Year FCF (£m) | B3: 10667 | C3: FY2024 free cash flow (author’s figure). BP reports in US$: confirm currency.
A4: FCF Growth Rate (Years 1–5) | B4: 0.02 | C4: Conservative assumption
A5: Discount Rate (WACC) | B5: 0.08 | C5: Assumed WACC for a large oil major
A6: Terminal Growth Rate | B6: 0.015 | C6: Long-term GDP-type growth
A7: Net Debt (£m) | B7: 25187 | C7: From balance sheet (author’s figure). One figure used throughout.
A8: Shares Outstanding (m) | B8: 15700 | C8: ≈15.7bn ordinary shares (Trading Economics, Sept 2026)
A9: Current Share Price (£) | B9: 5.423 | C9: 542.3p on 22 Sept 2026 (Trading Economics)

Sheet FCF Projection
A1: Free Cash Flow Projection
A2: Year | B2: FCF (£m) | C2: Growth % | D2: Discount Factor
A3: 0 | B3: =Assumptions!B3 -> 10667
A4: 1 | B4: =B3*(1+Assumptions!$B$4) -> 10880.34 | C4: =Assumptions!$B$4 -> 0.02 | D4: =1/(1+Assumptions!$B$5)^1 -> 0.92592593
A5: 2 | B5: =B4*(1+Assumptions!$B$4) -> 11097.947 | C5: =Assumptions!$B$4 -> 0.02 | D5: =1/(1+Assumptions!$B$5)^2 -> 0.85733882
A6: 3 | B6: =B5*(1+Assumptions!$B$4) -> 11319.906 | C6: =Assumptions!$B$4 -> 0.02 | D6: =1/(1+Assumptions!$B$5)^3 -> 0.79383224
A7: 4 | B7: =B6*(1+Assumptions!$B$4) -> 11546.304 | C7: =Assumptions!$B$4 -> 0.02 | D7: =1/(1+Assumptions!$B$5)^4 -> 0.73502985
A8: 5 | B8: =B7*(1+Assumptions!$B$4) -> 11777.23 | C8: =Assumptions!$B$4 -> 0.02 | D8: =1/(1+Assumptions!$B$5)^5 -> 0.6805832

Sheet EV Build-Up
A1: Present Value, Terminal Value & Enterprise Value
A2: Year | B2: FCF (£m) | C2: Discount Factor | D2: PV (£m)
A3: 1 | B3: ='FCF Projection'!B4 -> 10880.34 | C3: ='FCF Projection'!D4 -> 0.92592593 | D3: =B3*C3 -> 10074.389
A4: 2 | B4: ='FCF Projection'!B5 -> 11097.947 | C4: ='FCF Projection'!D5 -> 0.85733882 | D4: =B4*C4 -> 9514.7006
A5: 3 | B5: ='FCF Projection'!B6 -> 11319.906 | C5: ='FCF Projection'!D6 -> 0.79383224 | D5: =B5*C5 -> 8986.1061
A6: 4 | B6: ='FCF Projection'!B7 -> 11546.304 | C6: ='FCF Projection'!D7 -> 0.73502985 | D6: =B6*C6 -> 8486.878
A7: 5 | B7: ='FCF Projection'!B8 -> 11777.23 | C7: ='FCF Projection'!D8 -> 0.6805832 | D7: =B7*C7 -> 8015.3848
A9: Item | B9: £m
A10: PV of FCF (Years 1–5) | B10: =SUM(D3:D7) -> 45077.458
A11: Terminal Value at Year 5 | B11: =B7*(1+Assumptions!B6)/(Assumptions!B5-Assumptions!B6) -> 183905.98
A12: PV of Terminal Value | B12: =B11*C7 -> 125163.32
A13: Enterprise Value | B13: =B10+B12 -> 170240.77
A14: Terminal value as % of EV | B14: =B12/B13 -> 0.7352135

Sheet Equity Value
A1: Equity Value & Implied Share Price
A2: Item | B2: Value
A3: Enterprise Value (£m) | B3: ='EV Build-Up'!B13 -> 170240.77
A4: Less: Net Debt (£m) | B4: =Assumptions!B7 -> 25187
A5: Equity Value (£m) | B5: =B3-B4 -> 145053.77
A6: Shares Outstanding (m) | B6: =Assumptions!B8 -> 15700
A7: Implied Share Price (£) | B7: =B5/B6 -> 9.2390939
A8: Current Share Price (£) | B8: =Assumptions!B9 -> 5.423
A9: Implied Upside / (Downside) | B9: =B7/B8-1 -> 0.70368688

Sheet Sensitivity
A1: Implied Share Price (£): WACC vs Terminal Growth
A2: Rows: terminal growth. Columns: WACC. Each cell recalculates the full DCF.
A3: g \ WACC | B3: 0.07 | C3: 0.075 | D3: 0.08 | E3: 0.085 | F3: 0.09
A4: 0.01 | B4: =((Assumptions!$B$3*(1+Assumptions!$B$4)^1/(1+B$3)^1+Assumptions!$B$3*(1+Assumptions!$B$4)^2/(1+B$3)^2+Assumptions!$B$3*(1+Assumptions!$B$4)^3/(1+B$3)^3+Assumptions!$B$3*(1+Assumptions!$B$4)^4/(1+B$3)^4+Assumptions!$B$3*(1+Assumptions!$B$4)^5/(1+B$3)^5)+Assumptions!$B$3*(1+Assumptions!$B$4)^5*(1+$A4)/(B$3-$A4)/(1+B$3)^5-Assumptions!$B$7)/Assumptions!$B$8 -> 10.348439 | C4: =((Assumptions!$B$3*(1+Assumptions!$B$4)^1/(1+C$3)^1+Assumptions!$B$3*(1+Assumptions!$B$4)^2/(1+C$3)^2+Assumptions!$B$3*(1+Assumptions!$B$4)^3/(1+C$3)^3+Assumptions!$B$3*(1+Assumptions!$B$4)^4/(1+C$3)^4+Assumptions!$B$3*(1+Assumptions!$B$4)^5/(1+C$3)^5)+Assumptions!$B$3*(1+Assumptions!$B$4)^5*(1+$A4)/(C$3-$A4)/(1+C$3)^5-Assumptions!$B$7)/Assumptions!$B$8 -> 9.4248027 | D4: =((Assumptions!$B$3*(1+Assumptions!$B$4)^1/(1+D$3)^1+Assumptions!$B$3*(1+Assumptions!$B$4)^2/(1+D$3)^2+Assumptions!$B$3*(1+Assumptions!$B$4)^3/(1+D$3)^3+Assumptions!$B$3*(1+Assumptions!$B$4)^4/(1+D$3)^4+Assumptions!$B$3*(1+Assumptions!$B$4)^5/(1+D$3)^5)+Assumptions!$B$3*(1+Assumptions!$B$4)^5*(1+$A4)/(D$3-$A4)/(1+D$3)^5-Assumptions!$B$7)/Assumptions!$B$8 -> 8.6331854 | E4: =((Assumptions!$B$3*(1+Assumptions!$B$4)^1/(1+E$3)^1+Assumptions!$B$3*(1+Assumptions!$B$4)^2/(1+E$3)^2+Assumptions!$B$3*(1+Assumptions!$B$4)^3/(1+E$3)^3+Assumptions!$B$3*(1+Assumptions!$B$4)^4/(1+E$3)^4+Assumptions!$B$3*(1+Assumptions!$B$4)^5/(1+E$3)^5)+Assumptions!$B$3*(1+Assumptions!$B$4)^5*(1+$A4)/(E$3-$A4)/(1+E$3)^5-Assumptions!$B$7)/Assumptions!$B$8 -> 7.9471816 | F4: =((Assumptions!$B$3*(1+Assumptions!$B$4)^1/(1+F$3)^1+Assumptions!$B$3*(1+Assumptions!$B$4)^2/(1+F$3)^2+Assumptions!$B$3*(1+Assumptions!$B$4)^3/(1+F$3)^3+Assumptions!$B$3*(1+Assumptions!$B$4)^4/(1+F$3)^4+Assumptions!$B$3*(1+Assumptions!$B$4)^5/(1+F$3)^5)+Assumptions!$B$3*(1+Assumptions!$B$4)^5*(1+$A4)/(F$3-$A4)/(1+F$3)^5-Assumptions!$B$7)/Assumptions!$B$8 -> 7.3469874
A5: 0.0125 | B5: =((Assumptions!$B$3*(1+Assumptions!$B$4)^1/(1+B$3)^1+Assumptions!$B$3*(1+Assumptions!$B$4)^2/(1+B$3)^2+Assumptions!$B$3*(1+Assumptions!$B$4)^3/(1+B$3)^3+Assumptions!$B$3*(1+Assumptions!$B$4)^4/(1+B$3)^4+Assumptions!$B$3*(1+Assumptions!$B$4)^5/(1+B$3)^5)+Assumptions!$B$3*(1+Assumptions!$B$4)^5*(1+$A5)/(B$3-$A5)/(1+B$3)^5-Assumptions!$B$7)/Assumptions!$B$8 -> 10.763134 | C5: =((Assumptions!$B$3*(1+Assumptions!$B$4)^1/(1+C$3)^1+Assumptions!$B$3*(1+Assumptions!$B$4)^2/(1+C$3)^2+Assumptions!$B$3*(1+Assumptions!$B$4)^3/(1+C$3)^3+Assumptions!$B$3*(1+Assumptions!$B$4)^4/(1+C$3)^4+Assumptions!$B$3*(1+Assumptions!$B$4)^5/(1+C$3)^5)+Assumptions!$B$3*(1+Assumptions!$B$4)^5*(1+$A5)/(C$3-$A5)/(1+C$3)^5-Assumptions!$B$7)/Assumptions!$B$8 -> 9.7704684 | D5: =((Assumptions!$B$3*(1+Assumptions!$B$4)^1/(1+D$3)^1+Assumptions!$B$3*(1+Assumptions!$B$4)^2/(1+D$3)^2+Assumptions!$B$3*(1+Assumptions!$B$4)^3/(1+D$3)^3+Assumptions!$B$3*(1+Assumptions!$B$4)^4/(1+D$3)^4+Assumptions!$B$3*(1+Assumptions!$B$4)^5/(1+D$3)^5)+Assumptions!$B$3*(1+Assumptions!$B$4)^5*(1+$A5)/(D$3-$A5)/(1+D$3)^5-Assumptions!$B$7)/Assumptions!$B$8 -> 8.9249191 | E5: =((Assumptions!$B$3*(1+Assumptions!$B$4)^1/(1+E$3)^1+Assumptions!$B$3*(1+Assumptions!$B$4)^2/(1+E$3)^2+Assumptions!$B$3*(1+Assumptions!$B$4)^3/(1+E$3)^3+Assumptions!$B$3*(1+Assumptions!$B$4)^4/(1+E$3)^4+Assumptions!$B$3*(1+Assumptions!$B$4)^5/(1+E$3)^5)+Assumptions!$B$3*(1+Assumptions!$B$4)^5*(1+$A5)/(E$3-$A5)/(1+E$3)^5-Assumptions!$B$7)/Assumptions!$B$8 -> 8.1960474 | F5: =((Assumptions!$B$3*(1+Assumptions!$B$4)^1/(1+F$3)^1+Assumptions!$B$3*(1+Assumptions!$B$4)^2/(1+F$3)^2+Assumptions!$B$3*(1+Assumptions!$B$4)^3/(1+F$3)^3+Assumptions!$B$3*(1+Assumptions!$B$4)^4/(1+F$3)^4+Assumptions!$B$3*(1+Assumptions!$B$4)^5/(1+F$3)^5)+Assumptions!$B$3*(1+Assumptions!$B$4)^5*(1+$A5)/(F$3-$A5)/(1+F$3)^5-Assumptions!$B$7)/Assumptions!$B$8 -> 7.5612695
A6: 0.015 | B6: =((Assumptions!$B$3*(1+Assumptions!$B$4)^1/(1+B$3)^1+Assumptions!$B$3*(1+Assumptions!$B$4)^2/(1+B$3)^2+Assumptions!$B$3*(1+Assumptions!$B$4)^3/(1+B$3)^3+Assumptions!$B$3*(1+Assumptions!$B$4)^4/(1+B$3)^4+Assumptions!$B$3*(1+Assumptions!$B$4)^5/(1+B$3)^5)+Assumptions!$B$3*(1+Assumptions!$B$4)^5*(1+$A6)/(B$3-$A6)/(1+B$3)^5-Assumptions!$B$7)/Assumptions!$B$8 -> 11.21553 | C6: =((Assumptions!$B$3*(1+Assumptions!$B$4)^1/(1+C$3)^1+Assumptions!$B$3*(1+Assumptions!$B$4)^2/(1+C$3)^2+Assumptions!$B$3*(1+Assumptions!$B$4)^3/(1+C$3)^3+Assumptions!$B$3*(1+Assumptions!$B$4)^4/(1+C$3)^4+Assumptions!$B$3*(1+Assumptions!$B$4)^5/(1+C$3)^5)+Assumptions!$B$3*(1+Assumptions!$B$4)^5*(1+$A6)/(C$3-$A6)/(1+C$3)^5-Assumptions!$B$7)/Assumptions!$B$8 -> 10.14494 | D6: =((Assumptions!$B$3*(1+Assumptions!$B$4)^1/(1+D$3)^1+Assumptions!$B$3*(1+Assumptions!$B$4)^2/(1+D$3)^2+Assumptions!$B$3*(1+Assumptions!$B$4)^3/(1+D$3)^3+Assumptions!$B$3*(1+Assumptions!$B$4)^4/(1+D$3)^4+Assumptions!$B$3*(1+Assumptions!$B$4)^5/(1+D$3)^5)+Assumptions!$B$3*(1+Assumptions!$B$4)^5*(1+$A6)/(D$3-$A6)/(1+D$3)^5-Assumptions!$B$7)/Assumptions!$B$8 -> 9.2390939 | E6: =((Assumptions!$B$3*(1+Assumptions!$B$4)^1/(1+E$3)^1+Assumptions!$B$3*(1+Assumptions!$B$4)^2/(1+E$3)^2+Assumptions!$B$3*(1+Assumptions!$B$4)^3/(1+E$3)^3+Assumptions!$B$3*(1+Assumptions!$B$4)^4/(1+E$3)^4+Assumptions!$B$3*(1+Assumptions!$B$4)^5/(1+E$3)^5)+Assumptions!$B$3*(1+Assumptions!$B$4)^5*(1+$A6)/(E$3-$A6)/(1+E$3)^5-Assumptions!$B$7)/Assumptions!$B$8 -> 8.4626894 | F6: =((Assumptions!$B$3*(1+Assumptions!$B$4)^1/(1+F$3)^1+Assumptions!$B$3*(1+Assumptions!$B$4)^2/(1+F$3)^2+Assumptions!$B$3*(1+Assumptions!$B$4)^3/(1+F$3)^3+Assumptions!$B$3*(1+Assumptions!$B$4)^4/(1+F$3)^4+Assumptions!$B$3*(1+Assumptions!$B$4)^5/(1+F$3)^5)+Assumptions!$B$3*(1+Assumptions!$B$4)^5*(1+$A6)/(F$3-$A6)/(1+F$3)^5-Assumptions!$B$7)/Assumptions!$B$8 -> 7.789837
A7: 0.0175 | B7: =((Assumptions!$B$3*(1+Assumptions!$B$4)^1/(1+B$3)^1+Assumptions!$B$3*(1+Assumptions!$B$4)^2/(1+B$3)^2+Assumptions!$B$3*(1+Assumptions!$B$4)^3/(1+B$3)^3+Assumptions!$B$3*(1+Assumptions!$B$4)^4/(1+B$3)^4+Assumptions!$B$3*(1+Assumptions!$B$4)^5/(1+B$3)^5)+Assumptions!$B$3*(1+Assumptions!$B$4)^5*(1+$A7)/(B$3-$A7)/(1+B$3)^5-Assumptions!$B$7)/Assumptions!$B$8 -> 11.71101 | C7: =((Assumptions!$B$3*(1+Assumptions!$B$4)^1/(1+C$3)^1+Assumptions!$B$3*(1+Assumptions!$B$4)^2/(1+C$3)^2+Assumptions!$B$3*(1+Assumptions!$B$4)^3/(1+C$3)^3+Assumptions!$B$3*(1+Assumptions!$B$4)^4/(1+C$3)^4+Assumptions!$B$3*(1+Assumptions!$B$4)^5/(1+C$3)^5)+Assumptions!$B$3*(1+Assumptions!$B$4)^5*(1+$A7)/(C$3-$A7)/(1+C$3)^5-Assumptions!$B$7)/Assumptions!$B$8 -> 10.551973 | D7: =((Assumptions!$B$3*(1+Assumptions!$B$4)^1/(1+D$3)^1+Assumptions!$B$3*(1+Assumptions!$B$4)^2/(1+D$3)^2+Assumptions!$B$3*(1+Assumptions!$B$4)^3/(1+D$3)^3+Assumptions!$B$3*(1+Assumptions!$B$4)^4/(1+D$3)^4+Assumptions!$B$3*(1+Assumptions!$B$4)^5/(1+D$3)^5)+Assumptions!$B$3*(1+Assumptions!$B$4)^5*(1+$A7)/(D$3-$A7)/(1+D$3)^5-Assumptions!$B$7)/Assumptions!$B$8 -> 9.5784027 | E7: =((Assumptions!$B$3*(1+Assumptions!$B$4)^1/(1+E$3)^1+Assumptions!$B$3*(1+Assumptions!$B$4)^2/(1+E$3)^2+Assumptions!$B$3*(1+Assumptions!$B$4)^3/(1+E$3)^3+Assumptions!$B$3*(1+Assumptions!$B$4)^4/(1+E$3)^4+Assumptions!$B$3*(1+Assumptions!$B$4)^5/(1+E$3)^5)+Assumptions!$B$3*(1+Assumptions!$B$4)^5*(1+$A7)/(E$3-$A7)/(1+E$3)^5-Assumptions!$B$7)/Assumptions!$B$8 -> 8.7490826 | F7: =((Assumptions!$B$3*(1+Assumptions!$B$4)^1/(1+F$3)^1+Assumptions!$B$3*(1+Assumptions!$B$4)^2/(1+F$3)^2+Assumptions!$B$3*(1+Assumptions!$B$4)^3/(1+F$3)^3+Assumptions!$B$3*(1+Assumptions!$B$4)^4/(1+F$3)^4+Assumptions!$B$3*(1+Assumptions!$B$4)^5/(1+F$3)^5)+Assumptions!$B$3*(1+Assumptions!$B$4)^5*(1+$A7)/(F$3-$A7)/(1+F$3)^5-Assumptions!$B$7)/Assumptions!$B$8 -> 8.0341678
A8: 0.02 | B8: =((Assumptions!$B$3*(1+Assumptions!$B$4)^1/(1+B$3)^1+Assumptions!$B$3*(1+Assumptions!$B$4)^2/(1+B$3)^2+Assumptions!$B$3*(1+Assumptions!$B$4)^3/(1+B$3)^3+Assumptions!$B$3*(1+Assumptions!$B$4)^4/(1+B$3)^4+Assumptions!$B$3*(1+Assumptions!$B$4)^5/(1+B$3)^5)+Assumptions!$B$3*(1+Assumptions!$B$4)^5*(1+$A8)/(B$3-$A8)/(1+B$3)^5-Assumptions!$B$7)/Assumptions!$B$8 -> 12.256038 | C8: =((Assumptions!$B$3*(1+Assumptions!$B$4)^1/(1+C$3)^1+Assumptions!$B$3*(1+Assumptions!$B$4)^2/(1+C$3)^2+Assumptions!$B$3*(1+Assumptions!$B$4)^3/(1+C$3)^3+Assumptions!$B$3*(1+Assumptions!$B$4)^4/(1+C$3)^4+Assumptions!$B$3*(1+Assumptions!$B$4)^5/(1+C$3)^5)+Assumptions!$B$3*(1+Assumptions!$B$4)^5*(1+$A8)/(C$3-$A8)/(1+C$3)^5-Assumptions!$B$7)/Assumptions!$B$8 -> 10.99601 | D8: =((Assumptions!$B$3*(1+Assumptions!$B$4)^1/(1+D$3)^1+Assumptions!$B$3*(1+Assumptions!$B$4)^2/(1+D$3)^2+Assumptions!$B$3*(1+Assumptions!$B$4)^3/(1+D$3)^3+Assumptions!$B$3*(1+Assumptions!$B$4)^4/(1+D$3)^4+Assumptions!$B$3*(1+Assumptions!$B$4)^5/(1+D$3)^5)+Assumptions!$B$3*(1+Assumptions!$B$4)^5*(1+$A8)/(D$3-$A8)/(1+D$3)^5-Assumptions!$B$7)/Assumptions!$B$8 -> 9.9459873 | E8: =((Assumptions!$B$3*(1+Assumptions!$B$4)^1/(1+E$3)^1+Assumptions!$B$3*(1+Assumptions!$B$4)^2/(1+E$3)^2+Assumptions!$B$3*(1+Assumptions!$B$4)^3/(1+E$3)^3+Assumptions!$B$3*(1+Assumptions!$B$4)^4/(1+E$3)^4+Assumptions!$B$3*(1+Assumptions!$B$4)^5/(1+E$3)^5)+Assumptions!$B$3*(1+Assumptions!$B$4)^5*(1+$A8)/(E$3-$A8)/(1+E$3)^5-Assumptions!$B$7)/Assumptions!$B$8 -> 9.0575061 | F8: =((Assumptions!$B$3*(1+Assumptions!$B$4)^1/(1+F$3)^1+Assumptions!$B$3*(1+Assumptions!$B$4)^2/(1+F$3)^2+Assumptions!$B$3*(1+Assumptions!$B$4)^3/(1+F$3)^3+Assumptions!$B$3*(1+Assumptions!$B$4)^4/(1+F$3)^4+Assumptions!$B$3*(1+Assumptions!$B$4)^5/(1+F$3)^5)+Assumptions!$B$3*(1+Assumptions!$B$4)^5*(1+$A8)/(F$3-$A8)/(1+F$3)^5-Assumptions!$B$7)/Assumptions!$B$8 -> 8.2959509
A10: Base case (8.0% WACC, 1.5% growth) should match the Equity Value sheet.
